<annotation>
	<folder>train</folder>
	<filename>364.jpeg</filename>
	<path>C:\tensorflow1\models\research\object_detection\images\train\364.jpeg</path>
	<source>
		<database>Unknown</database>
	</source>
	<size>
		<width>1300</width>
		<height>940</height>
		<depth>3</depth>
	</size>
	<segmented>0</segmented>
	<object>
		<name>studentcopying</name>
		<pose>Unspecified</pose>
		<truncated>1</truncated>
		<difficult>0</difficult>
		<bndbox>
			<xmin>884</xmin>
			<ymin>158</ymin>
			<xmax>1300</xmax>
			<ymax>765</ymax>
		</bndbox>
	</object>
	<object>
		<name>studentcopying</name>
		<pose>Unspecified</pose>
		<truncated>0</truncated>
		<difficult>0</difficult>
		<bndbox>
			<xmin>7</xmin>
			<ymin>160</ymin>
			<xmax>643</xmax>
			<ymax>829</ymax>
		</bndbox>
	</object>
	<object>
		<name>chit</name>
		<pose>Unspecified</pose>
		<truncated>0</truncated>
		<difficult>0</difficult>
		<bndbox>
			<xmin>333</xmin>
			<ymin>518</ymin>
			<xmax>653</xmax>
			<ymax>825</ymax>
		</bndbox>
	</object>
	<object>
		<name>invigilator</name>
		<pose>Unspecified</pose>
		<truncated>0</truncated>
		<difficult>0</difficult>
		<bndbox>
			<xmin>526</xmin>
			<ymin>61</ymin>
			<xmax>671</xmax>
			<ymax>728</ymax>
		</bndbox>
	</object>
	<object>
		<name>student</name>
		<pose>Unspecified</pose>
		<truncated>0</truncated>
		<difficult>0</difficult>
		<bndbox>
			<xmin>265</xmin>
			<ymin>262</ymin>
			<xmax>484</xmax>
			<ymax>516</ymax>
		</bndbox>
	</object>
	<object>
		<name>student</name>
		<pose>Unspecified</pose>
		<truncated>0</truncated>
		<difficult>0</difficult>
		<bndbox>
			<xmin>686</xmin>
			<ymin>263</ymin>
			<xmax>820</xmax>
			<ymax>435</ymax>
		</bndbox>
	</object>
</annotation>
