<annotation>
	<folder>train</folder>
	<filename>31.jpeg</filename>
	<path>C:\tensorflow1\models\research\object_detection\images\train\31.jpeg</path>
	<source>
		<database>Unknown</database>
	</source>
	<size>
		<width>1200</width>
		<height>800</height>
		<depth>3</depth>
	</size>
	<segmented>0</segmented>
	<object>
		<name>student_copying</name>
		<pose>Unspecified</pose>
		<truncated>0</truncated>
		<difficult>0</difficult>
		<bndbox>
			<xmin>562</xmin>
			<ymin>105</ymin>
			<xmax>1103</xmax>
			<ymax>659</ymax>
		</bndbox>
	</object>
</annotation>
